hiagent_current_time_mcp/__init__.py
hiagent_current_time_mcp/server.py
hiagent_current_time_mcp-0.1.3.dist-info/METADATA
hiagent_current_time_mcp-0.1.3.dist-info/WHEEL
hiagent_current_time_mcp-0.1.3.dist-info/entry_points.txt
hiagent_current_time_mcp-0.1.3.dist-info/top_level.txt
hiagent_current_time_mcp-0.1.3.dist-info/RECORD
