Metadata-Version: 2.4
Name: hiagent_current_time_mcp
Version: 0.1.3
Summary: The MCP server to get local time
Requires-Python: >=3.10
Requires-Dist: fastmcp>=2.14.2
